django_datadog/__init__.py
django_datadog/compat.py
django_datadog/tests.py
django_datadog/utils.py
django_datadog_compatibility-0.0.1.dist-info/DESCRIPTION.rst
django_datadog_compatibility-0.0.1.dist-info/METADATA
django_datadog_compatibility-0.0.1.dist-info/RECORD
django_datadog_compatibility-0.0.1.dist-info/WHEEL
django_datadog_compatibility-0.0.1.dist-info/metadata.json
django_datadog_compatibility-0.0.1.dist-info/top_level.txt
