Metadata-Version: 2.0
Name: django-datadog-compatibility
Version: 0.0.1
Summary: A simple DataDog Integration for Django
Home-page: https://github.com/mypebble/django-datadog
Author: SF Software limited t/a Pebble
Author-email: sysadmin@mypebble.co.uk
License: MIT
Platform: UNKNOWN
Classifier: Development Status :: 5 - Production/Stable
Classifier: Intended Audience :: Developers
Classifier: License :: OSI Approved :: MIT License
Classifier: Operating System :: OS Independent
Classifier: Programming Language :: Python
Classifier: Programming Language :: Python :: 2.7
Classifier: Programming Language :: Python :: 3.5
Classifier: Topic :: Software Development :: Libraries :: Python Modules
Classifier: Framework :: Django
Requires-Dist: six
Requires-Dist: datadog
Requires-Dist: django
